CHANGELOG.md
LICENSE
MANIFEST.in
README.md
coverage_results-python3.6.txt
coverage_results-python3.9.txt
deliver-LO.sh
deliver.sh
setup.cfg
setup.py
tu.sh
./tu.sh
src/pypos3dtu/__init__.py
src/pypos3dtu/tuConst.py
src/pypos3dtu/tuDSON.py
src/pypos3dtu/tuFigure.py
src/pypos3dtu/tuGeomGroup.py
src/pypos3dtu/tuLangUtil.py
src/pypos3dtu/tuPaveList.py
src/pypos3dtu/tuPlaneCut.py
src/pypos3dtu/tuPoser11.py
src/pypos3dtu/tuPoser12.py
src/pypos3dtu/tuPoserFile.py
src/pypos3dtu/tuPoserMeshed.py
src/pypos3dtu/tuQSlim.py
src/pypos3dtu/tuUVRender.py
src/pypos3dtu/tuWFBasic.py
src/pypos3dtu/tuWaveGeom.py
src/pypos3dtu/tvViewer.py
src/pypos3dtu.egg-info/PKG-INFO
src/pypos3dtu.egg-info/SOURCES.txt
src/pypos3dtu.egg-info/dependency_links.txt
src/pypos3dtu.egg-info/requires.txt
src/pypos3dtu.egg-info/top_level.txt
src/pypos3dtu/srcdata/01Top_Hole.mtl
src/pypos3dtu/srcdata/01top_hole.obj
src/pypos3dtu/srcdata/A1-Poser12.pz3
src/pypos3dtu/srcdata/Caudron460-Exp.mtl
src/pypos3dtu/srcdata/Caudron460-Exp.obj
src/pypos3dtu/srcdata/Convex.obj
src/pypos3dtu/srcdata/Cube-NegIdx.obj
src/pypos3dtu/srcdata/Cube1DupFace.obj
src/pypos3dtu/srcdata/CubeTestBaryCentre.mtl
src/pypos3dtu/srcdata/CubeTestBaryCentre.obj
src/pypos3dtu/srcdata/CubesDupVerts-01.obj
src/pypos3dtu/srcdata/CubesDupVerts-02.obj
src/pypos3dtu/srcdata/Cup.obz
src/pypos3dtu/srcdata/Cutter-Convev+Dents.wings
src/pypos3dtu/srcdata/CutterCubeTriy0_25.mtl
src/pypos3dtu/srcdata/CutterCubeTriy0_25.obj
src/pypos3dtu/srcdata/CutterCubes.mtl
src/pypos3dtu/srcdata/CutterCubes.obj
src/pypos3dtu/srcdata/CutterCubey0_25.mtl
src/pypos3dtu/srcdata/CutterCubey0_25.obj
src/pypos3dtu/srcdata/CutterCubey0_252Optim.obj
src/pypos3dtu/srcdata/CutterCubey0_25Tex.mtl
src/pypos3dtu/srcdata/CutterCubey0_25Tex.obj
src/pypos3dtu/srcdata/CutterCylindre0.mtl
src/pypos3dtu/srcdata/CutterCylindre0.obj
src/pypos3dtu/srcdata/CutterT1.mtl
src/pypos3dtu/srcdata/CutterT1.obj
src/pypos3dtu/srcdata/CutterT1.wings
src/pypos3dtu/srcdata/CutterT2.mtl
src/pypos3dtu/srcdata/CutterT2.obj
src/pypos3dtu/srcdata/CutterT2.wings
src/pypos3dtu/srcdata/CutterT3-Mirror.obj
src/pypos3dtu/srcdata/CutterT3.wings
src/pypos3dtu/srcdata/CutterT4-Manchon.mtl
