Metadata-Version: 2.1
Name: pypos3dtu
Version: 2.3.0
Summary: Unit Tests for Wavefront files and Poser files manipulation library
Home-page: https://sourceforge.net/projects/pojamas
Author: Olivier Dufailly
Author-email: dufgrinder@laposte.net
License: UNKNOWN
Platform: UNKNOWN
Classifier: Development Status :: 4 - Beta
Classifier: Programming Language :: Python :: 3
Classifier: License :: OSI Approved :: BSD License
Classifier: Operating System :: OS Independent
Requires-Python: >=3.6
License-File: LICENSE
